agent.py
cli.py
config.py
llm.py
main.py
tools/__init__.py
tools/base.py
tools/code_executor.py
tools/file_ops.py
tools/scrape.py
tools/search.py
web_research_agent-1.2.0.dist-info/licenses/LICENSE
web_research_agent-1.2.0.dist-info/METADATA
web_research_agent-1.2.0.dist-info/WHEEL
web_research_agent-1.2.0.dist-info/entry_points.txt
web_research_agent-1.2.0.dist-info/top_level.txt
web_research_agent-1.2.0.dist-info/RECORD
