Metadata-Version: 2.4
Name: web-research-agent
Version: 1.2.0
Summary: An AI agent using ReAct methodology for autonomous web research tasks
Home-page: https://github.com/victorashioya/web_research_agent
Author: Victor Jotham Ashioya
Author-email: Victor Jotham Ashioya <victorashioya960@gmail.com>
Maintainer-email: Victor Jotham Ashioya <victorashioya960@gmail.com>
License: MIT
Project-URL: Homepage, https://github.com/victorashioya/web_research_agent
Project-URL: Documentation, https://github.com/victorashioya/web_research_agent#readme
Project-URL: Repository, https://github.com/victorashioya/web_research_agent
Project-URL: Bug Tracker, https://github.com/victorashioya/web_research_agent/issues
Project-URL: Changelog, https://github.com/victorashioya/web_research_agent/blob/main/CHANGELOG.md
Keywords: ai,agent,research,web-scraping,llm,gemini,react,autonomous-agent,web-research,information-retrieval
Classifier: Development Status :: 4 - Beta
Classifier: Intended Audience :: Developers
Classifier: Intended Audience :: Science/Research
Classifier: License :: OSI Approved :: MIT License
Classifier: Operating System :: OS Independent
Classifier: Programming Language :: Python :: 3
Classifier: Programming Language :: Python :: 3.8
Classifier: Programming Language :: Python :: 3.9
Classifier: Programming Language :: Python :: 3.10
Classifier: Programming Language :: Python :: 3.11
Classifier: Programming Language :: Python :: 3.12
Classifier: Programming Language :: Python :: 3.13
Classifier: Topic :: Scientific/Engineering :: Artificial Intelligence
Classifier: Topic :: Software Development :: Libraries :: Python Modules
Classifier: Topic :: Internet :: WWW/HTTP :: Dynamic Content
Classifier: Natural Language :: English
Requires-Python: >=3.8
License-File: LICENSE
Requires-Dist: google-generativeai>=0.8.0
Requires-Dist: requests>=2.32.0
Requires-Dist: beautifulsoup4>=4.12.0
Requires-Dist: html2text>=2024.2.0
Requires-Dist: python-dotenv>=1.0.0
Requires-Dist: colorama>=0.4.6
Provides-Extra: dev
Requires-Dist: pytest>=7.0.0; extra == "dev"
Requires-Dist: black>=22.0.0; extra == "dev"
Requires-Dist: flake8>=4.0.0; extra == "dev"
Requires-Dist: mypy>=0.950; extra == "dev"
Dynamic: author
Dynamic: home-page
Dynamic: license-file
Dynamic: requires-python
